irorun/__init__.py
irorun/cli.py
irorun/helpers.py
irorun/logger_setup.py
irorun/py.typed
irorun-0.1.0.dist-info/METADATA
irorun-0.1.0.dist-info/WHEEL
irorun-0.1.0.dist-info/entry_points.txt
irorun-0.1.0.dist-info/licenses/LICENSE.txt
irorun-0.1.0.dist-info/RECORD
