Metadata-Version: 2.4
Name: irorun
Version: 0.1.0
Summary: A unified CLI tool for bootstrapping Python projects with integrated code quality checks, formatting, and documentation generation. Designed for research teams, it automates environment setup with pre-configured scientific libraries, streamlining development so scientists can focus on their research.
Author-email: Faith Oyedemi <faithoyedemi@gmail.com>
License: Apache-2.0
License-File: LICENSE.txt
Classifier: License :: OSI Approved :: Apache Software License
Requires-Python: >=3.11
Requires-Dist: numpydoc>=1.8.0
Requires-Dist: poetry>=2.1.1
Requires-Dist: pylint>=3.3.4
Requires-Dist: pytest-cov>=6.0.0
Requires-Dist: pytest>=8.3.4
Requires-Dist: ruff>=0.9.9
Requires-Dist: sphinx>=8.2.1
Requires-Dist: toml>=0.10.2
Requires-Dist: typer>=0.15.2
Requires-Dist: virtualenv>=20.29.2
